BCD.v
module BCD(clk,rst_asyn,Load,Din,Q_out,Q);
input clk;
input rst_asyn,Load;
input [3:0]Din;
output [3:0]Q;
reg [3:0]Q;
output [6:0]Q_out;
reg [6:0]Q_out;

always@ (posedge clk)
begin

if (!rst_asyn)
    Q=0;
else if (Load)
    Q=Din;
else if (Q == 9)
    Q=0;
else
    Q+=1;
end

always@ (*)
begin
    case (Q)
        4'b0000 : Q_out = 7'b1000000;
        4'b0001 : Q_out = 7'b1111001;
        4'b0010 : Q_out = 7'b0100100;
        4'b0011 : Q_out = 7'b0110000;
        4'b0100 : Q_out = 7'b0011001;
        4'b0101 : Q_out = 7'b0010010;
        4'b0110 : Q_out = 7'b0000010;
        4'b0111 : Q_out = 7'b1111000;
        4'b1000 : Q_out = 7'b0000000;
        4'b1001 : Q_out = 7'b0010000;
        default : Q_out = 7'b0000000;
    endcase
end
endmodule

BCD_tb.v
module  BCD_tb;
  reg clk,rst_asyn,Load;
  reg [3:0]Din;
  wire [3:0]Q;
  wire [6:0]Q_out;
  parameter PERIOD=20;
  parameter real DUTY_CYCLE=0.5;
  parameter OFFSET=0;
initial begin
  #OFFSET;
  forever begin
    clk=1'b1;
    #(PERIOD-(PERIOD*DUTY_CYCLE)) clk=1'b0;
    #(PERIOD*DUTY_CYCLE);
  end
end
initial begin
  Din= 4'b0010;
  rst_asyn=1'b0;
  Load=1'b1;
  #5   rst_asyn=1'b1;
  #10  Load=1'b0;
  #50  rst_asyn=1'b0;
  #10  Load=1'b1;
  #5   rst_asyn=1'b1;
  #10  Load=1'b0;
  #200 $finish;
end
initial begin
$dumpfile("BCD.vcd");
  $dumpvars(0, BCD_tb);
end
  BCD BCD_tb(
    .clk(clk),
    .rst_asyn(rst_asyn),
    .Load(Load),
    .Din(Din),
    .Q_out(Q_out),
    .Q(Q)
  );
endmodule

BCD.vcd
$date
	Wed May 04 22:36:46 2022
$end
$version
	Icarus Verilog
$end
$timescale
	1s
$end
$scope module BCD_tb $end
$scope module BCD_tb $end
$var wire 4 ! Din [3:0] $end
$var wire 1 " Load $end
$var wire 1 # clk $end
$var wire 1 $ rst_asyn $end
$var reg 4 % Q [3:0] $end
$var reg 7 & Q_out [6:0] $end
$upscope $end
$upscope $end
$enddefinitions $end
#0
$dumpvars
b1000000 &
b0 %
0$
1#
1"
b10 !
$end
#5
1$
#10
0#
#15
0"
#20
b1111001 &
b1 %
1#
#30
0#
#40
b100100 &
b10 %
1#
#50
0#
#60
b110000 &
b11 %
1#
#65
0$
#70
0#
#75
1"
#80
b100100 &
b10 %
1$
1#
#90
0"
0#
#100
b110000 &
b11 %
1#
#110
0#
#120
b11001 &
b100 %
1#
#130
0#
#140
b10010 &
b101 %
1#
#150
0#
#160
b10 &
b110 %
1#
#170
0#
#180
b1111000 &
b111 %
1#
#190
0#
#200
b0 &
b1000 %
1#
#210
0#
#220
b10000 &
b1001 %
1#
#230
0#
#240
b1000000 &
b0 %
1#
#250
0#
#260
b1111001 &
b1 %
1#
#270
0#
#280
b100100 &
b10 %
1#
